[
  {
    "symbol": "00700",
    "name": "腾讯控股",
    "signal": "BUY",
    "score": 70,
    "confidence": 0.7,
    "current_price": 50.01,
    "change_pct": 3.24,
    "recommendation": "建议买入",
    "timestamp": "2026-05-04T14:00:45.070964"
  },
  {
    "symbol": "09988",
    "name": "阿里巴巴-SW",
    "signal": "BUY",
    "score": 65,
    "confidence": 0.6,
    "current_price": 160.91,
    "change_pct": 3.58,
    "recommendation": "建议买入",
    "timestamp": "2026-05-04T14:00:45.071018"
  },
  {
    "symbol": "03690",
    "name": "美团-W",
    "signal": "BUY",
    "score": 65,
    "confidence": 0.6,
    "current_price": 393.05,
    "change_pct": 4.89,
    "recommendation": "建议买入",
    "timestamp": "2026-05-04T14:00:45.071054"
  },
  {
    "symbol": "01810",
    "name": "小米集团-W",
    "signal": "WEAK_SELL",
    "score": 45,
    "confidence": 0.4,
    "current_price": 229.82,
    "change_pct": -0.8,
    "recommendation": "谨慎持有",
    "timestamp": "2026-05-04T14:00:45.071083"
  },
  {
    "symbol": "00981",
    "name": "中芯国际",
    "signal": "BUY",
    "score": 70,
    "confidence": 0.7,
    "current_price": 142.76,
    "change_pct": 4.05,
    "recommendation": "建议买入",
    "timestamp": "2026-05-04T14:00:45.071089"
  },
  {
    "symbol": "01299",
    "name": "友邦保险",
    "signal": "WEAK_BUY",
    "score": 55,
    "confidence": 0.4,
    "current_price": 13.76,
    "change_pct": 1.31,
    "recommendation": "可以关注",
    "timestamp": "2026-05-04T14:00:45.071122"
  },
  {
    "symbol": "02318",
    "name": "中国平安",
    "signal": "BUY",
    "score": 70,
    "confidence": 0.7,
    "current_price": 13.02,
    "change_pct": 2.27,
    "recommendation": "建议买入",
    "timestamp": "2026-05-04T14:00:45.071127"
  },
  {
    "symbol": "03988",
    "name": "中国银行",
    "signal": "BUY",
    "score": 70,
    "confidence": 0.7,
    "current_price": 289.08,
    "change_pct": 4.08,
    "recommendation": "建议买入",
    "timestamp": "2026-05-04T14:00:45.071155"
  },
  {
    "symbol": "00005",
    "name": "汇丰控股",
    "signal": "SELL",
    "score": 35,
    "confidence": 0.6,
    "current_price": 409.42,
    "change_pct": -4.09,
    "recommendation": "建议卖出",
    "timestamp": "2026-05-04T14:00:45.071183"
  },
  {
    "symbol": "00883",
    "name": "中国海洋石油",
    "signal": "SELL",
    "score": 35,
    "confidence": 0.6,
    "current_price": 16.54,
    "change_pct": -2.41,
    "recommendation": "建议卖出",
    "timestamp": "2026-05-04T14:00:45.071209"
  },
  {
    "symbol": "00857",
    "name": "中国石油股份",
    "signal": "SELL",
    "score": 35,
    "confidence": 0.6,
    "current_price": 308.56,
    "change_pct": -2.7,
    "recommendation": "建议卖出",
    "timestamp": "2026-05-04T14:00:45.071235"
  },
  {
    "symbol": "00386",
    "name": "中国石油化工",
    "signal": "BUY",
    "score": 65,
    "confidence": 0.6,
    "current_price": 115.25,
    "change_pct": 2.68,
    "recommendation": "建议买入",
    "timestamp": "2026-05-04T14:00:45.071260"
  },
  {
    "symbol": "02331",
    "name": "李宁",
    "signal": "BUY",
    "score": 70,
    "confidence": 0.7,
    "current_price": 146.0,
    "change_pct": 3.16,
    "recommendation": "建议买入",
    "timestamp": "2026-05-04T14:00:45.071289"
  },
  {
    "symbol": "02020",
    "name": "安踏体育",
    "signal": "BUY",
    "score": 65,
    "confidence": 0.6,
    "current_price": 306.09,
    "change_pct": 2.86,
    "recommendation": "建议买入",
    "timestamp": "2026-05-04T14:00:45.071315"
  },
  {
    "symbol": "06186",
    "name": "中国飞鹤",
    "signal": "WEAK_BUY",
    "score": 55,
    "confidence": 0.4,
    "current_price": 98.46,
    "change_pct": 1.52,
    "recommendation": "可以关注",
    "timestamp": "2026-05-04T14:00:45.071346"
  },
  {
    "symbol": "02269",
    "name": "药明生物",
    "signal": "BUY",
    "score": 70,
    "confidence": 0.7,
    "current_price": 144.52,
    "change_pct": 2.9,
    "recommendation": "建议买入",
    "timestamp": "2026-05-04T14:00:45.071351"
  },
  {
    "symbol": "01093",
    "name": "石药集团",
    "signal": "WEAK_SELL",
    "score": 50,
    "confidence": 0.3,
    "current_price": 167.82,
    "change_pct": -1.08,
    "recommendation": "观望",
    "timestamp": "2026-05-04T14:00:45.071378"
  },
  {
    "symbol": "02359",
    "name": "药明康德",
    "signal": "WEAK_SELL",
    "score": 45,
    "confidence": 0.4,
    "current_price": 352.95,
    "change_pct": -0.6,
    "recommendation": "谨慎持有",
    "timestamp": "2026-05-04T14:00:45.071384"
  },
  {
    "symbol": "09618",
    "name": "京东集团-SW",
    "signal": "SELL",
    "score": 40,
    "confidence": 0.5,
    "current_price": 330.57,
    "change_pct": -3.07,
    "recommendation": "建议卖出",
    "timestamp": "2026-05-04T14:00:45.071389"
  },
  {
    "symbol": "09888",
    "name": "百度集团-SW",
    "signal": "BUY",
    "score": 65,
    "confidence": 0.6,
    "current_price": 59.29,
    "change_pct": 4.45,
    "recommendation": "建议买入",
    "timestamp": "2026-05-04T14:00:45.071417"
  }
]