{
  "id": "@a5l/skill-stock-five-steps",
  "kind": "tool",
  "version": "2.1.0",
  "domain": "investment-analysis",
  "created_at": "2026-05-11T01:23:32.915280",
  "edges": {
    "requires": [
      "@a5l/skill-fundamental-analysis"
    ],
    "enhances": [
      "@a5l/decision-support"
    ],
    "validates_with": [],
    "contradicts": [],
    "related": [
      "@a5l/skill-factor-investing",
      "@a5l/skill-unified-stock-price",
      "@a5l/skill-fx-factor-monitor",
      "@a5l/skill-private-banker-stock",
      "@a5l/skill-buffett-value-investing"
    ],
    "derived_from": []
  },
  "content": {
    "name": "stock-five-steps",
    "description": "Five-step stock analysis framework for systematic evaluation. Use for structured investment analysis from business to outlook.",
    "trigger_words": [
      "/\u4e2a\u80a1\u5206\u6790",
      "/\u4e94\u6b65\u6cd5",
      "/\u5206\u6790"
    ],
    "source_path": "skills/stock-five-steps/SKILL.md"
  }
}