{
  "title": "A5L Architecture Evolution Roadmap",
  "version": "1.0.0",
  "current_phase": "P4",
  "phases": {
    "P5_agentification": {
      "name": "智能体化",
      "timeline": "本月 (May 2026)",
      "objectives": [
        "增强Layer 0自主决策能力",
        "实现各层作为独立Agent",
        "多智能体协作机制",
        "自然语言意图理解"
      ],
      "deliverables": [
        "AutonomousDecisionEngine",
        "MultiAgentOrchestrator",
        "IntentUnderstandingModule",
        "AgentCommunicationProtocol"
      ],
      "success_criteria": [
        "80%任务可自动决策",
        "自然语言指令理解准确率>90%",
        "多Agent协作延迟<100ms"
      ]
    },
    "P6_production": {
      "name": "产品化",
      "timeline": "下月 (June 2026)",
      "objectives": [
        "Web界面完整版",
        "API接口标准化",
        "文档自动化",
        "容器化部署"
      ],
      "deliverables": [
        "InteractiveWebDashboard",
        "StandardizedAPI",
        "AutoDocumentation",
        "DockerKubernetesSupport"
      ],
      "success_criteria": [
        "Web界面覆盖100%功能",
        "API响应时间<200ms",
        "文档实时更新",
        "一键部署完成"
      ]
    },
    "P7_ecosystem": {
      "name": "生态系统",
      "timeline": "本季度 (Q3 2026)",
      "objectives": [
        "插件市场",
        "策略市场",
        "数据市场",
        "社区功能"
      ],
      "deliverables": [
        "PluginMarketplace",
        "StrategyMarketplace",
        "DataMarketplace",
        "CommunityPlatform"
      ],
      "success_criteria": [
        "10+第三方插件",
        "20+公开策略",
        "5+数据源接入",
        "活跃社区用户>100"
      ]
    },
    "P8_autonomous_evolution": {
      "name": "自主进化",
      "timeline": "长期 (2027+)",
      "objectives": [
        "自我发现问题",
        "自主开发功能",
        "策略自我优化",
        "架构自我重构"
      ],
      "deliverables": [
        "SelfDiscoveryEngine",
        "AutoDevelopmentModule",
        "SelfOptimizationEngine",
        "ArchitectureEvolutionEngine"
      ],
      "success_criteria": [
        "自动发现90%问题",
        "自主开发简单功能",
        "策略参数自动优化",
        "架构调整无需人工"
      ]
    }
  },
  "iteration_mechanism": {
    "cycle": "Observe → Analyze → Design → Implement → Verify → Deploy",
    "frequency": "Weekly sprints, Monthly releases",
    "feedback_loops": [
      "User feedback collection",
      "Performance metrics analysis",
      "Error pattern recognition",
      "Improvement proposal generation"
    ]
  }
}